djangochurch_data/__init__.py
djangochurch_data/apps.py
djangochurch_data/models.py
djangochurch_data/fixtures/djangochurch_assets.json
djangochurch_data/fixtures/djangochurch_events.json
djangochurch_data/fixtures/djangochurch_news.json
djangochurch_data/fixtures/djangochurch_pages.json
djangochurch_data/images/remember.jpg
djangochurch_data/images/sample-image-1.jpg
djangochurch_data/images/sample-image-2.jpg
djangochurch_data/images/sample-image-3.jpg
djangochurch_data/images/sample-image-4.jpg
djangochurch_data/management/__init__.py
djangochurch_data/management/commands/__init__.py
djangochurch_data/management/commands/djangochurchimages.py
djangochurch_data-0.1.2.dist-info/DESCRIPTION.rst
djangochurch_data-0.1.2.dist-info/METADATA
djangochurch_data-0.1.2.dist-info/RECORD
djangochurch_data-0.1.2.dist-info/WHEEL
djangochurch_data-0.1.2.dist-info/metadata.json
djangochurch_data-0.1.2.dist-info/top_level.txt
